probe_sdk/__init__.py
probe_sdk/value_detect_client.py
probe_sdk-0.1.0.dist-info/licenses/LICENSE
probe_sdk-0.1.0.dist-info/METADATA
probe_sdk-0.1.0.dist-info/WHEEL
probe_sdk-0.1.0.dist-info/top_level.txt
probe_sdk-0.1.0.dist-info/RECORD
