Metadata-Version: 2.4
Name: probe_sdk
Version: 0.1.0
Summary: A probe SDK for value detection
Author-email: xuzhihong <xzh@bigai.com>
Requires-Python: >=3.8
License-File: LICENSE
Requires-Dist: requests>=2.0.0
Dynamic: license-file
